Metadata-Version: 1.1
Name: dongo
Version: 0.4.0
Summary: A Django-ORM inspired Mongo ODM.
Home-page: https://github.com/johannestaas/dongo
Author: Johan Nestaas
Author-email: johannestaas@gmail.com
License: LGPLv3+
Platform: UNKNOWN
Classifier: Development Status :: 3 - Alpha
Classifier: License :: OSI Approved :: GNU Lesser General Public License v3 or later (LGPLv3+)
Classifier: Environment :: Console
Classifier: Environment :: X11 Applications :: Qt
Classifier: Environment :: MacOS X
Classifier: Environment :: Win32 (MS Windows)
Classifier: Operating System :: POSIX
Classifier: Operating System :: MacOS :: MacOS X
Classifier: Operating System :: Microsoft :: Windows
Classifier: Programming Language :: Python
